ut_xml/__init__.py
ut_xml/__version__.py
ut_xml/aob.py
ut_xml/aox.py
ut_xml/py.typed
ut_xml/xml.py
ut_xml/xml2dic.py
ut_xml/xml2dic2.py
ut_xml/xml2dicapc.py
ut_xml-2.0.0.20251021.dist-info/licenses/LICENSE.txt
ut_xml-2.0.0.20251021.dist-info/METADATA
ut_xml-2.0.0.20251021.dist-info/WHEEL
ut_xml-2.0.0.20251021.dist-info/entry_points.txt
ut_xml-2.0.0.20251021.dist-info/top_level.txt
ut_xml-2.0.0.20251021.dist-info/RECORD
