Metadata-Version: 2.4
Name: ut_xml
Version: 2.0.0.20251021
Summary: Xml Utilities
Author-email: Bernd Stroehle <bernd.stroehle@gmail.com>
Maintainer-email: Bernd Stroehle <bernd.stroehle@gmail.com>
License-Expression: GPL-3.0-only WITH Classpath-exception-2.0 OR BSD-3-Clause
Project-URL: Source Code, https://github.com/bs2910/ut_xml/tree/master
Project-URL: Homepage, https://kosakya.de/
Project-URL: Documentation, https://ka-com.readthedocs.io/en/latest
Classifier: Development Status :: 5 - Production/Stable
Classifier: Intended Audience :: Developers
Classifier: Operating System :: OS Independent
Classifier: Programming Language :: Python :: 3.12
Classifier: Natural Language :: English
Classifier: Topic :: Software Development :: Libraries :: Python Modules
Requires-Python: >=3.10
License-File: LICENSE.txt
Requires-Dist: lxml>=5.4.0
Requires-Dist: xmltodict>=0.14.2
Requires-Dist: ut_dic>=1.0.0.20250913
Requires-Dist: ut_obj>=1.0.0.20250913
Dynamic: license-file
